CHANGELOG.txt
LICENSE.txt
MANIFEST.in
README.txt
setup.py
netack/__init__.py
netack.egg-info/PKG-INFO
netack.egg-info/SOURCES.txt
netack.egg-info/dependency_links.txt
netack.egg-info/requires.txt
netack.egg-info/top_level.txt