Metadata-Version: 1.1
Name: netack
Version: 0.0.7
Summary: python library for basic network attacks
Home-page: UNKNOWN
Author: akash sharma and akshat sharma
Author-email: UNKNOWN
License: UNKNOWN
Keywords: network security
Platform: UNKNOWN
Classifier: Development Status :: 5 - Production/Stable
Classifier: Intended Audience :: Education
Classifier: Operating System :: POSIX :: Linux
Classifier: License :: OSI Approved :: MIT License
Classifier: Programming Language :: Python :: 3
Classifier: Programming Language :: Python :: 3.4
Classifier: Programming Language :: Python :: 3.5
Classifier: Programming Language :: Python :: 3.6
Classifier: Programming Language :: Python :: 3.7
Classifier: Programming Language :: Python :: 3.8
Classifier: Programming Language :: Python :: 3.9
